LICENSE.txt
MANIFEST.in
README.md
VERSION
setup.cfg
setup.py
./ude/__init__.py
./ude/exception.py
./ude/gym_ude.py
./ude/serialization_context.py
./ude/ude_typing.py
./ude/communication/__init__.py
./ude/communication/constants.py
./ude/communication/grpc_auth.py
./ude/communication/grpc_auth_interceptor.py
./ude/communication/ude_client.py
./ude/communication/ude_server.py
./ude/environment/__init__.py
./ude/environment/constants.py
./ude/environment/interfaces.py
./ude/environment/ude_environment.py
./ude/environment/adapters/__init__.py
./ude/environment/adapters/remote_environment_adapter.py
./ude/side_channels/__init__.py
./ude/side_channels/constants.py
./ude/side_channels/ude_side_channel.py
./ude/side_channels/adapters/__init__.py
./ude/side_channels/adapters/dummy_side_channel.py
./ude/side_channels/adapters/single_side_channel.py
./ude/ude_objects/__init__.py
./ude/ude_objects/ude_data_message_pb2.py
./ude/ude_objects/ude_data_message_pb2_grpc.py
./ude/ude_objects/ude_empty_message_pb2.py
./ude/ude_objects/ude_empty_message_pb2_grpc.py
./ude/ude_objects/ude_message_pb2.py
./ude/ude_objects/ude_message_pb2_grpc.py
./ude/ude_objects/ude_pb2.py
./ude/ude_objects/ude_pb2_grpc.py
./ude/ude_objects/ude_side_channel_message_pb2.py
./ude/ude_objects/ude_side_channel_message_pb2_grpc.py
test/test_ude_import.py
ude.egg-info/PKG-INFO
ude.egg-info/SOURCES.txt
ude.egg-info/dependency_links.txt
ude.egg-info/requires.txt
ude.egg-info/top_level.txt