Metadata-Version: 2.1
Name: ude
Version: 0.1.5
Summary: UDE: A reinforcement learning environment virtualization framework.
Home-page: https://github.com/aws-deepracer/ude
Author: Amazon Web Services
License: Apache License 2.0
Keywords: ML RL Amazon AWS AI
Platform: UNKNOWN
Classifier: Development Status :: 4 - Beta
Classifier: Intended Audience :: Developers
Classifier: Natural Language :: English
Classifier: License :: OSI Approved :: Apache Software License
Classifier: Programming Language :: Python
Classifier: Programming Language :: Python :: 3.6
Classifier: Programming Language :: Python :: 3.7
Classifier: Programming Language :: Python :: 3.8
Classifier: Programming Language :: Python :: 3.9
License-File: LICENSE.txt
